CHANGES.txt
MANIFEST.in
NEWS.txt
README.rst
setup.py
bin/run_montecarlo.py
pyrings.egg-info/PKG-INFO
pyrings.egg-info/SOURCES.txt
pyrings.egg-info/dependency_links.txt
pyrings.egg-info/requires.txt
pyrings.egg-info/top_level.txt
pyrings.egg-info/zip-safe
rings/__init__.py
rings/fitt.py
rings/ring.py
rings/utils.py
rings/misc/__init__.py
rings/misc/montecarlo.py
rings/test/__init__.py