Metadata-Version: 1.1
Name: pyrings
Version: 0.7.6
Summary: Procedures to handle coherent vortexes in the ocean
Home-page: http://pyrings.castelao.net
Author: Guilherme Castelao, Luiz Irber, Ana Villas Boas
Author-email: guilherme@castelao.net, luiz.irber@gmail.com
License: PSF
Download-URL: https://pypi.python.org/packages/source/p/pyrings/
Keywords: rings,eddies,ADCP,Gradient Balance
Platform: any
Classifier: Development Status :: 4 - Beta
Classifier: Environment :: Console
Classifier: Intended Audience :: Science/Research
Classifier: Intended Audience :: Developers
Classifier: License :: OSI Approved :: Python Software Foundation License
Classifier: Operating System :: OS Independent
Classifier: Programming Language :: Python :: 2.6
Classifier: Programming Language :: Python :: 2.7
Classifier: Topic :: Scientific/Engineering
Classifier: Topic :: Software Development :: Libraries :: Python Modules
